{
  "project_info": {
    "project_number": "989158188177",
    "project_id": "dopamine-game",
    "storage_bucket": "dopamine-game.firebasestorage.app"
  },
  "client": [
    {
      "client_info": {
        "mobilesdk_app_id": "1:989158188177:android:bc844f06fe049c1f01cb30",
        "android_client_info": {
          "package_name": "com.example.app"
        }
      },
      "oauth_client": [
        {
          "client_id": "989158188177-1srfsmi3q2euoqgja8v8o3jcsobhveg5.apps.googleusercontent.com",
          "client_type": 1,
          "android_info": {
            "package_name": "com.example.app",
            "certificate_hash": "7e3f1d8b5ad3f6527e3c18112cb64999c9cab4e9"
          }
        },
        {
          "client_id": "989158188177-hjk0bdkcqv9pl06g7vd4in0n43r03r7m.apps.googleusercontent.com",
          "client_type": 3
        }
      ],
      "api_key": [
        {
          "current_key": "AIzaSyCT2OKGvF4ONR1kBQ9sXat7n_2W_ngRfm0"
        }
      ],
      "services": {
        "appinvite_service": {
          "other_platform_oauth_client": [
            {
              "client_id": "989158188177-hjk0bdkcqv9pl06g7vd4in0n43r03r7m.apps.googleusercontent.com",
              "client_type": 3
            },
            {
              "client_id": "989158188177-na6jtfd6rl24g3qggtihcok1j0n0t06d.apps.googleusercontent.com",
              "client_type": 2,
              "ios_info": {
                "bundle_id": "com.google.firebase.presents.demo"
              }
            }
          ]
        }
      }
    }
  ],
  "configuration_version": "1"
}